iamport/__init__.py
iamport-0.0.1.dist-info/METADATA
iamport-0.0.1.dist-info/WHEEL
iamport-0.0.1.dist-info/top_level.txt
iamport-0.0.1.dist-info/RECORD
